rabbitmq_json_sender/__init__.py
rabbitmq_json_sender/clickhouse_client.py
rabbitmq_json_sender/config.py
rabbitmq_json_sender/data_sync_api.py
rabbitmq_json_sender/field_mapping.py
rabbitmq_json_sender/main.py
rabbitmq_json_sender/rabbitmq_client.py
rabbitmq_json_sender/transform.py
rabbitmq_json_sender/universal_transform.py
rabbitmq_json_sender/usage_examples.py
rabbitmq_json_sender-0.1.4.dist-info/METADATA
rabbitmq_json_sender-0.1.4.dist-info/WHEEL
rabbitmq_json_sender-0.1.4.dist-info/entry_points.txt
rabbitmq_json_sender-0.1.4.dist-info/RECORD
