Metadata-Version: 2.4
Name: rabbitmq-json-sender
Version: 0.1.4
Summary: Universal ClickHouse to RabbitMQ data synchronization system with configurable field mappings
License: MIT
Keywords: rabbitmq,clickhouse,data-sync,etl
Author: Vladimir Muzychenko
Author-email: vladimir.muzychenko@gmail.com
Requires-Python: >=3.9,<4.0
Classifier: Development Status :: 4 - Beta
Classifier: Intended Audience :: Developers
Classifier: License :: OSI Approved :: MIT License
Classifier: Programming Language :: Python :: 3
Classifier: Programming Language :: Python :: 3.9
Classifier: Programming Language :: Python :: 3.10
Classifier: Programming Language :: Python :: 3.11
Classifier: Programming Language :: Python :: 3.12
Classifier: Programming Language :: Python :: 3.13
Classifier: Programming Language :: Python :: 3.14
Requires-Dist: attrs (>=25.3.0,<26.0.0)
Requires-Dist: certifi (>=2025.8.3,<2026.0.0)
Requires-Dist: clickhouse-connect (>=0.8.18,<0.9.0)
Requires-Dist: jsonschema (>=4.19.2,<5.0.0)
Requires-Dist: jsonschema-specifications (>=2025.4.1,<2026.0.0)
Requires-Dist: lz4 (>=4.4.4,<5.0.0)
Requires-Dist: pika (>=1.3.2,<2.0.0)
Requires-Dist: python-dotenv (>=1.0.0,<2.0.0)
Requires-Dist: pytz (>=2025.2,<2026.0)
Requires-Dist: referencing (>=0.36.2,<0.37.0)
Requires-Dist: rpds-py (>=0.27.1,<0.28.0)
Requires-Dist: urllib3 (>=2.5.0,<3.0.0)
Requires-Dist: zstandard (>=0.24.0,<0.25.0)
Project-URL: Homepage, https://github.com/yourusername/rabbitmq-json-sender
Project-URL: Repository, https://github.com/yourusername/rabbitmq-json-sender
